[
  {
    "name": "s12v55_jk_3m-ota-17.07.2019",
    "filename": "s12v55_jk_3m-ota-17.07.2019.zip",
    "md5": "c36738a536f270a225c98387540d9bcd",
    "size": 52865798,
    "builddate": 1563350964,
    "releasedate": 1563358089000,
    "device": "Blackview",
    "url": "https://vgdn1942.ocloud.de/index.php/s/zH2nJMCxGf6nonV/download",
    "patchlevel": "0",
    "changelog": [
      "Added tile on/off blue protection mode",
      "Added tile enable/disable processor information",
      "Changed the algorithm for holding the PTT button for on/off flashlight"
    ]
  },
  {
    "name": "s12v55_jk_3m-ota-11.07.2019",
    "filename": "s12v55_jk_3m-ota-11.07.2019.zip",
    "md5": "a4e33e7f70152e997870012221c12a96",
    "size": 62497533,
    "builddate": 1562867551,
    "releasedate": 1562873236000,
    "device": "Blackview",
    "url": "https://vgdn1942.ocloud.de/index.php/s/6M4X8V6EJ17JaeP/download",
    "patchlevel": "0",
    "changelog": [
      "Display bluetooth battery status when available in statusbar and QS Tile",
      "Add ToolBox instead Compass",
      "Add Cpu overlay",
      "Set default governor to conservative instead interactive"
    ]
  },
  {
    "name": "s12v55_jk_3m-ota-04.07.2019",
    "filename": "s12v55_jk_3m-ota-04.07.2019.zip",
    "md5": "af39792d91743ead1896d5929a1457fe",
    "size": 57264442,
    "builddate": 1562235668,
    "releasedate": 1562242151000,
    "device": "Blackview",
    "url": "https://vgdn1942.ocloud.de/index.php/s/DF3HCQQczbJJffy/download",
    "patchlevel": "0",
    "changelog": [
      "Added adjust the overall strength of vibration",
      "Added disabled full screen InCallUI",
      "Disable VILTE",
      "Video quality format WxH",
      "Video photo filename format dd.MM.yyyy_HH-mm-ss",
      "Icon H+ in statusbar"
    ]
  },
  {
    "name": "s12v55_jk_3m-ota-24.06.2019",
    "filename": "s12v55_jk_3m-ota-24.06.2019.zip",
    "md5": "4c826ebf6e719e294f0f811fb454a945",
    "size": 48352565,
    "builddate": 1561358158,
    "releasedate": 1561367387000,
    "device": "Blackview",
    "url": "https://vgdn1942.ocloud.de/index.php/s/KC8NcEgPRiYMf0L/download",
    "patchlevel": "0",
    "changelog": [
      "Fixing autorotation when off from the QS tile",
      "Correction of the non-inclusion of the button illumination when pressing the app switch button",
      "Notification backlight buttons"
    ]
  },
  {
    "name": "s12v55_jk_3m-ota-21.06.2019",
    "filename": "s12v55_jk_3m-ota-21.06.2019.zip",
    "md5": "55f4f03690f597ac61402b5760cbe6c8",
    "size": 176024213,
    "builddate": 1561112467,
    "releasedate": 1561116079000,
    "device": "Blackview",
    "url": "https://vgdn1942.ocloud.de/index.php/s/ei0dGLOUIm3SlhH/download",
    "patchlevel": "0",
    "changelog": [
      "Fixed actions to the PTT button",
      "Added actions for torch in screen on",
      "Fixed Voice Match in Google app",
      "Gesture V replace torch",
      "Configure dalvik in build.prop",
      "Fixed Marathon mode in Battery Saver",
      "Fixed Russian translate",
      "Added vibrate for screen gesture",
      "Added Rotation modes",
      "Added button backlight settings",
      "Added disabled dialog on battery full"
    ]
  },
  {
    "name": "s12v55_jk_3m-ota-19.06.2019",
    "filename": "s12v55_jk_3m-ota-19.06.2019.zip",
    "md5": "abbcee8bf249faba9fe34072a7917307",
    "size": 46198454,
    "builddate": 1560894770,
    "releasedate": 1560899576000,
    "device": "Blackview",
    "url": "https://vgdn1942.ocloud.de/index.php/s/LffCeBghiY6JENb/download",
    "patchlevel": "0",
    "changelog": [
      "Fixed Power Saving Mode/Battery Profiles",
      "Added more actions to the PTT button"
    ]
  },
  {
    "name": "s12v55_jk_3m-ota-15.06.2019",
    "filename": "s12v55_jk_3m-ota-15.06.2019.zip",
    "md5": "61eb5ca738881de17e99b56025a849a7",
    "size": 54957339,
    "builddate": 1560619416,
    "releasedate": 1560623458000,
    "device": "Blackview",
    "url": "https://vgdn1942.ocloud.de/index.php/s/O58WWebrPSgngOm/download",
    "patchlevel": "0",
    "changelog": [
      "Fix potentials memory leakages",
      "Added advanced selection of network type",
      "Units hPa (hPa/mbar) added to Compass",
      "Removed background file in Camera weighing almost 4mb",
      "Added icon to switch auto brightness in status bar",
      "Minor fix for LTE network level display in status bar"
    ]
  }
]
